monitus/__init__.py
monitus/middleware.py
tests/__init__.py
tests/async_urls.py
tests/settings.py
tests/test_async_middleware.py
tests/test_middleware.py
tests/urls.py
django_monitus-1.0.0.dist-info/LICENSE
django_monitus-1.0.0.dist-info/METADATA
django_monitus-1.0.0.dist-info/WHEEL
django_monitus-1.0.0.dist-info/top_level.txt
django_monitus-1.0.0.dist-info/RECORD
