Metadata-Version: 2.1
Name: django-monitus
Version: 1.0.0
Summary: Tiny error reporting middleware(s) for Django.
Home-page: https://github.com/valentinogagliardi/django-monitus
Author: Valentino Gagliardi
Author-email: valentino@valentinog.com
Maintainer: Valentino Gagliardi
License: MIT License
Project-URL: Twitter, https://twitter.com/gagliardi_vale
Keywords: django,middleware,notification,admins
Platform: UNKNOWN
Classifier: Development Status :: 4 - Beta
Classifier: Framework :: Django
Classifier: Framework :: Django :: 3.0
Classifier: Framework :: Django :: 3.1
Classifier: Intended Audience :: Developers
Classifier: License :: OSI Approved :: MIT License
Classifier: Programming Language :: Python
Classifier: Programming Language :: Python :: 3
Classifier: Programming Language :: Python :: 3.8
Requires-Python: >=3.7
Requires-Dist: Django (>=3.0)
